scdiffusionX/__init__.py
scdiffusionX/utils.py
scdiffusionX/Autoencoder/__init__.py
scdiffusionX/Autoencoder/__main__.py
scdiffusionX/Autoencoder/paths.py
scdiffusionX/Autoencoder/py.typed
scdiffusionX/Autoencoder/data/__init__.py
scdiffusionX/Autoencoder/data/scrnaseq_loader.py
scdiffusionX/Autoencoder/data/utils.py
scdiffusionX/Autoencoder/estimator/__init__.py
scdiffusionX/Autoencoder/estimator/encoder_estimator.py
scdiffusionX/Autoencoder/models/__init__.py
scdiffusionX/Autoencoder/models/base/__init__.py
scdiffusionX/Autoencoder/models/base/encoder_model.py
scdiffusionX/Autoencoder/models/base/utils.py
scdiffusionX/Autoencoder/models/featurizers/category_featurizer.py
scdiffusionX/DiffusionBackbone/__init__.py
scdiffusionX/DiffusionBackbone/common.py
scdiffusionX/DiffusionBackbone/dist_util.py
scdiffusionX/DiffusionBackbone/dpm_solver_plus.py
scdiffusionX/DiffusionBackbone/fp16_util.py
scdiffusionX/DiffusionBackbone/gaussian_diffusion.py
scdiffusionX/DiffusionBackbone/image_datasets.py
scdiffusionX/DiffusionBackbone/image_unet.py
scdiffusionX/DiffusionBackbone/logger.py
scdiffusionX/DiffusionBackbone/losses.py
scdiffusionX/DiffusionBackbone/multimodal_datasets.py
scdiffusionX/DiffusionBackbone/multimodal_dpm_solver_plus.py
scdiffusionX/DiffusionBackbone/multimodal_gaussian_diffusion.py
scdiffusionX/DiffusionBackbone/multimodal_respace.py
scdiffusionX/DiffusionBackbone/multimodal_script_util.py
scdiffusionX/DiffusionBackbone/multimodal_train_util.py
scdiffusionX/DiffusionBackbone/multimodal_unet.py
scdiffusionX/DiffusionBackbone/nn.py
scdiffusionX/DiffusionBackbone/optimization.py
scdiffusionX/DiffusionBackbone/real_image_datasets.py
scdiffusionX/DiffusionBackbone/resample.py
scdiffusionX/DiffusionBackbone/respace.py
scdiffusionX/DiffusionBackbone/script_util.py
scdiffusionX/DiffusionBackbone/train_util.py
scdiffusionx-0.0.2.dist-info/METADATA
scdiffusionx-0.0.2.dist-info/WHEEL
scdiffusionx-0.0.2.dist-info/licenses/LICENSE
scdiffusionx-0.0.2.dist-info/RECORD
