Metadata-Version: 2.4
Name: scdiffusionX
Version: 0.0.2
Summary: scDiffusion-X: Diffusion Model for Single-Cell Multiome Data Generation and Analysis
Project-URL: Homepage, https://github.com/EperLuo/scDiffusion-X
Project-URL: Issues, https://github.com/EperLuo/scDiffusion-X/issues
Author-email: Erpai Luo <lep23@mails.tsinghua.edu.cn>
License: BSD 3-Clause License
License-File: LICENSE
Classifier: Operating System :: OS Independent
Classifier: Programming Language :: Python :: 3
Requires-Python: >=3.8
Requires-Dist: blobfile>=2.0.0
Requires-Dist: click>=8.1.7
Requires-Dist: einops>=0.8.0
Requires-Dist: hydra-core>=1.3.2
Requires-Dist: hydra-optuna-sweeper>=1.2.0
Requires-Dist: hydra-submitit-launcher>=1.2.0
Requires-Dist: multiprocess>=0.70
Requires-Dist: muon>=0.1.6
Requires-Dist: numpy>=1.22.4
Requires-Dist: omegaconf>=2.3.0
Requires-Dist: pytorch-lightning<1.9.0
Requires-Dist: pyyaml>=6.0.2
Requires-Dist: rich>=13.9.4
Requires-Dist: scanpy>=1.9.1
Requires-Dist: scikit-learn>=1.2.2
Requires-Dist: scipy>=1.10.1
Requires-Dist: scvi-tools<=1.0.0
Requires-Dist: tensorboard>=2.12.0
Requires-Dist: torch>=2.1.2
Requires-Dist: torchvision>=0.14.0
Requires-Dist: tqdm>=4.64.1
Requires-Dist: wandb>=0.16.1
